lab_optimizer/__init__.py
lab_optimizer/agent_model.py
lab_optimizer/global_optimize.py
lab_optimizer/local_optimize.py
lab_optimizer/mloop_optimize.py
lab_optimizer/opt_examples.py
lab_optimizer/optimize_base.py
lab_optimizer/torch_optimize.py
lab_optimizer/units.py
lab_optimizer/opt_lib/ISMA.py
lab_optimizer/opt_lib/__init__.py
lab_optimizer/opt_lib/test_functions.py
lab_optimizer-1.3.1.dist-info/LICENSE
lab_optimizer-1.3.1.dist-info/METADATA
lab_optimizer-1.3.1.dist-info/WHEEL
lab_optimizer-1.3.1.dist-info/top_level.txt
lab_optimizer-1.3.1.dist-info/RECORD
