Metadata-Version: 2.2
Name: lab_optimizer
Version: 1.3.1
Summary: A collection of optimization algorithms
Home-page: https://github.com/quantumopticss/lab_optimizer
Author: Zifeng Li
Author-email: Zifeng Li <221503020@smail.nju.edu.cn>
License: MIT License
Project-URL: Homepage, https://github.com/quantumopticss/lab_optimizer
Requires-Python: >=3.10
License-File: LICENSE
Requires-Dist: M-LOOP>=3.3.5
Requires-Dist: scikit-opt>=0.6.6
Requires-Dist: scikit-learn>=1.2.2
Requires-Dist: numpy>=1.26.4
Requires-Dist: scipy>=1.14.0
Requires-Dist: matplotlib>=3.9.2
Requires-Dist: pandas>=1.5.3
Requires-Dist: seaborn>=0.12.2
Requires-Dist: plotly>=5.24.1
Requires-Dist: torch>=2.3.1
Dynamic: author
Dynamic: home-page
Dynamic: requires-python
